README.txt
setup.py
relocator/__init__.py
relocator/relocator.py
relocator/sample.py
relocator.egg-info/PKG-INFO
relocator.egg-info/SOURCES.txt
relocator.egg-info/dependency_links.txt
relocator.egg-info/entry_points.txt
relocator.egg-info/not-zip-safe
relocator.egg-info/requires.txt
relocator.egg-info/top_level.txt