Metadata-Version: 1.0
Name: relocator
Version: 0.1
Summary: change Location field in responses using WSGI middleware
Home-page: UNKNOWN
Author: Jeff Hammel
Author-email: jhammel@mozilla.com
License: MPL
Platform: UNKNOWN
